cooperative_dataclasses/__init__.py
cooperative_dataclasses/dataclasses.py
cooperative_dataclasses/mypy_plugin.py
cooperative_dataclasses/py.typed
cooperative_dataclasses-0.2.5.dist-info/LICENSE
cooperative_dataclasses-0.2.5.dist-info/WHEEL
cooperative_dataclasses-0.2.5.dist-info/METADATA
cooperative_dataclasses-0.2.5.dist-info/RECORD
